{
	"class" : {
		"addToWorldMenu" : "K.P. 5/27/2021 11:21",
		"allowedFileExtensions" : "mFr 6/26/2021 21:07",
		"borderColor" : "K.P. 5/29/2021 14:14",
		"borderWidth" : "mFr 5/26/2021 12:11",
		"canvasPanelBorder" : "mFr 5/26/2021 12:00",
		"newWith:" : "6/28/2021 21:03:28",
		"open" : "K.P. 5/27/2021 11:22",
		"openWith:" : "6/28/2021 21:03:28",
		"topPanelHeight" : "mFr 5/26/2021 12:02" },
	"instance" : {
		"activateDefaultItem" : "mFr 5/19/2021 11:03",
		"applyDefaultSettingsTo:" : "mFr 5/26/2021 11:59",
		"backend" : "mFr 5/19/2021 10:58",
		"brushMenu" : "mFr 5/19/2021 11:03",
		"brushSizeIndicator" : "mFr 7/1/2021 15:45",
		"brushSizeIndicator:" : "mFr 7/1/2021 15:46",
		"brushSizeSlider" : "mFr 5/26/2021 11:30",
		"brushSizeSlider:" : "mFr 5/26/2021 11:31",
		"canvas" : "mFr 5/19/2021 10:58",
		"canvas:" : "6/28/2021 21:03:28",
		"canvasPanel" : "mFr 5/19/2021 10:59",
		"canvasPanel:" : "mFr 5/19/2021 10:59",
		"chooseColor" : "CS 6/1/2021 19:10",
		"clearCanvas" : "mFr 5/19/2021 10:59",
		"clickMenuItemWith:" : "K.P. 8/1/2021 19:45",
		"colorPalette" : "mFr 5/19/2021 10:59",
		"colorPanel" : "mFr 5/19/2021 10:59",
		"colorPanel:" : "mFr 5/19/2021 10:59",
		"colorPicker" : "mFr 5/19/2021 10:59",
		"defaultBrushSizeIndicator" : "mFr 7/1/2021 15:45",
		"defaultBrushSizeSlider" : "CS 6/2/2021 14:56",
		"defaultColorPanelExtent" : "mFr 7/14/2021 17:38",
		"defaultColorPicker" : "CS 7/14/2021 19:02",
		"enableInsertSelectionButton" : "mFr 7/14/2021 16:54",
		"exportPNG" : "mFr 5/19/2021 11:00",
		"findMenuItemWith:" : "mFr 7/14/2021 16:57",
		"form" : "mFr 5/19/2021 11:00",
		"getNameOfFileToExport" : "mFr 5/19/2021 11:00",
		"getNameOfFileToImport" : "mFr 6/9/2021 17:50",
		"handleCommandKeystroke:" : "K.P. 7/8/2021 13:44",
		"handleKeystroke:" : "K.P. 8/1/2021 19:47",
		"handleNoModifierKeystroke:" : "K.P. 8/1/2021 19:49",
		"handleShiftKeystroke:" : "ms 7/9/2021 14:47",
		"handlesMouseDown:" : "K.P. 7/8/2021 16:52",
		"importImage" : "mFr 6/3/2021 21:17",
		"importImage:" : "mFr 6/3/2021 21:17",
		"initialize" : "mFr 7/14/2021 16:39",
		"initializeCanvasPanel" : "mk 7/27/2020 20:15",
		"initializeColorPanel" : "mFr 7/14/2021 17:37",
		"initializeMenuPanel" : "mFr 5/26/2021 12:21",
		"initializePanels" : "mk 7/27/2020 20:16",
		"initializeTopPanel" : "mFr 7/14/2021 17:09",
		"loadMenu" : "mFr 5/19/2021 12:45",
		"menuBrushCollection" : "CS 6/28/2021 21:28",
		"menuBrushCollection:" : "mFr 5/19/2021 12:17",
		"menuGeometricCollection" : "mFr 7/14/2021 16:35",
		"menuGeometricCollection:" : "mFr 5/19/2021 12:17",
		"menuMiscCollection" : "mFr 6/3/2021 21:16",
		"menuMiscCollection:" : "mFr 5/19/2021 12:17",
		"menuPanel" : "mFr 5/19/2021 10:57",
		"menuPanel:" : "mFr 5/19/2021 10:57",
		"minimumExtent" : "mFr 5/26/2021 12:05",
		"mouseDown:" : "K.P. 7/8/2021 16:55",
		"paneColor" : "6/28/2021 21:03:28",
		"pasteClipboard" : "ms 7/7/2021 18:11",
		"setColor:" : "ms 6/16/2021 10:33",
		"submenuDict" : "mFr 5/26/2021 11:54",
		"submenuDict:" : "mFr 5/19/2021 12:23",
		"topPanel" : "mFr 5/19/2021 10:58",
		"topPanel:" : "mFr 5/19/2021 10:58",
		"undo" : "mFr 5/19/2021 10:58",
		"viewPort" : "6/28/2021 21:03:28" } }
