{
	"class" : {
		 },
	"instance" : {
		"brushSize" : "wr 5/14/2020 16:42",
		"brushSize:" : "mk 5/10/2020 20:37",
		"defaultBounds" : "mk 5/8/2020 12:32",
		"defaultBrushSize" : "wr 5/14/2020 16:38",
		"defaultDepth" : "mk 5/8/2020 12:12",
		"defaultForm" : "mk 5/8/2020 12:28",
		"defaultPencilSize" : "mk 5/10/2020 20:32",
		"defaultRectangleBrushSize" : "mk 5/10/2020 20:44",
		"drawCircle" : "wr 5/14/2020 16:47",
		"drawPencil" : "wr 5/11/2020 12:58",
		"drawRectangle" : "wr 5/11/2020 12:57",
		"drawTriangle" : "wr 5/14/2020 16:41",
		"form" : "mk 5/8/2020 12:27",
		"form:" : "mk 5/8/2020 11:45",
		"formSize:" : "mk 5/8/2020 13:05",
		"initialize" : "mk 5/8/2020 12:00",
		"pen" : "NC 5/14/2020 09:37",
		"pen:" : "NC 5/9/2020 20:04",
		"penNibOffset" : "wr 5/14/2020 16:26",
		"pencilSize" : "mk 5/10/2020 20:34",
		"pencilSize:" : "mk 5/10/2020 20:34",
		"rectangleBrushSize" : "mk 5/10/2020 20:44",
		"rectangleBrushSize:" : "mk 5/10/2020 20:44",
		"setPenDown:" : "mp 5/11/2020 17:11",
		"sourceForm" : "CCJ 5/13/2020 16:07" } }
